yt_ripper/__init__.py
yt_ripper/main.py
yt_ripper/cli/__init__.py
yt_ripper/cli/loading.py
yt_ripper/cli/menu.py
yt_ripper/cli/youtube.py
yt_ripper/path/__init__.py
yt_ripper/path/utils.py
yt_ripper-0.0.9.dist-info/METADATA
yt_ripper-0.0.9.dist-info/WHEEL
yt_ripper-0.0.9.dist-info/entry_points.txt
yt_ripper-0.0.9.dist-info/top_level.txt
yt_ripper-0.0.9.dist-info/RECORD
