Metadata-Version: 2.1
Name: yt-ripper
Version: 0.0.9
Summary: Project with Python to download videos and mp3 files of youtube in the terminal
Home-page: https://github.com/atticus64/yt_ripper
Author: Jonathani Atticus64
Author-email: jonaenglish64@gmail.com
Keywords: youtube
Classifier: Programming Language :: Python :: 3
Classifier: License :: OSI Approved :: MIT License
Classifier: Operating System :: POSIX :: Linux
Classifier: Topic :: Terminals :: Terminal Emulators/X Terminals
Requires-Python: >=3.6
Requires-Dist: colorama
Requires-Dist: pytube
Requires-Dist: tqdm
